{
  "tasks": [
    {
      "title": "Learn Redux",
      "description": "The store, actions, and reducers, oh my!",
      "status": "Unstarted",
      "timer": 4,
      "id": 1
    },
    {
      "title": "Peace on Earth",
      "description": "No big deal.",
      "status": "Unstarted",
      "timer": 62,
      "id": 2
    },
    {
      "id": 3,
      "title": "Create Facebook for dogs",
      "description": "The hottest new social network",
      "status": "Completed",
      "timer": 0
    }
  ]
}